outagelab/__init__.py
outagelab/outagelab.py
outagelab-0.2.0.dist-info/AUTHORS.rst
outagelab-0.2.0.dist-info/LICENSE
outagelab-0.2.0.dist-info/METADATA
outagelab-0.2.0.dist-info/WHEEL
outagelab-0.2.0.dist-info/top_level.txt
outagelab-0.2.0.dist-info/RECORD
