Metadata-Version: 2.1
Name: outagelab
Version: 0.2.0
Summary: Outage simulation
Author-email: Max North <maxwelldnorth@gmail.com>
Maintainer-email: Max North <maxwelldnorth@gmail.com>
License: MIT license
Project-URL: bugs, https://github.com/maxnorth/outagelab/issues
Project-URL: changelog, https://github.com/maxnorth/outagelab/blob/master/changelog.md
Project-URL: homepage, https://github.com/maxnorth/outagelab
License-File: LICENSE
License-File: AUTHORS.rst
Requires-Dist: requests
Provides-Extra: dev
Requires-Dist: coverage ; extra == 'dev'
Requires-Dist: mypy ; extra == 'dev'
Requires-Dist: pytest ; extra == 'dev'
Requires-Dist: ruff ; extra == 'dev'
